LICENSE
MANIFEST.in
README.rst
setup.py
lyricaly/__init__.py
lyricaly/__main__.py
lyricaly.egg-info/PKG-INFO
lyricaly.egg-info/SOURCES.txt
lyricaly.egg-info/dependency_links.txt
lyricaly.egg-info/entry_points.txt
lyricaly.egg-info/not-zip-safe
lyricaly.egg-info/requires.txt
lyricaly.egg-info/top_level.txt