Metadata-Version: 1.1
Name: lyricaly
Version: 1.0.5
Summary: Lyricaly Gets Lyrics directly to your Terminal.
Home-page: https://github.com/vigzmv/Lyricaly
Author: Vignesh M
Author-email: vigzmv@outlook.com
License: MIT License
Download-URL: https://github.com/vigzmv/Lyricaly
Keywords: lyrics vigzmv music songs lyricaly vignesh m
Platform: UNKNOWN
